kohtaaminen/__init__.py
kohtaaminen/__main__.py
kohtaaminen/cli.py
kohtaaminen/kohtaaminen.py
test/__init__.py
test/context.py
test/test_cli.py
test/test_kohtaaminen.py
kohtaaminen-2022.8.2.dist-info/LICENSE
kohtaaminen-2022.8.2.dist-info/METADATA
kohtaaminen-2022.8.2.dist-info/WHEEL
kohtaaminen-2022.8.2.dist-info/entry_points.txt
kohtaaminen-2022.8.2.dist-info/top_level.txt
kohtaaminen-2022.8.2.dist-info/RECORD
