Metadata-Version: 2.1
Name: kohtaaminen
Version: 2022.8.2
Summary: Meeting, rendezvous, confluence (Finnish: kohtaaminen) mark up, down, and up again.
Home-page: https://git.sr.ht/~sthagen/kohtaaminen
Author: Stefan Hagen
Author-email: stefan@hagen.link
Maintainer: Stefan Hagen
Maintainer-email: stefan@hagen.link
Project-URL: Bug Tracker, https://todo.sr.ht/~sthagen/kohtaaminen
Project-URL: Documentation, https://codes.dilettant.life/docs/kohtaaminen
Project-URL: Source Code, https://git.sr.ht/~sthagen/kohtaaminen
Project-URL: Test Coverage, https://codes.dilettant.life/coverage/kohtaaminen
Keywords: developer-tools,documentation-tools,html,markdown
Classifier: Development Status :: 3 - Alpha
Classifier: Intended Audience :: Developers
Classifier: License :: OSI Approved :: MIT License
Classifier: Programming Language :: Python :: 3.10
Classifier: Programming Language :: Python :: 3.8
Classifier: Programming Language :: Python :: 3.9
Requires-Python: >=3.8
License-File: LICENSE
Requires-Dist: mdformat-gfm (>=0.3.5)
Requires-Dist: pypandoc (>=1.8.1)
Requires-Dist: typer (>=0.6.1)
Provides-Extra: dev
Requires-Dist: black ; extra == 'dev'
Requires-Dist: coverage ; extra == 'dev'
Requires-Dist: flake8 ; extra == 'dev'
Requires-Dist: mypy ; extra == 'dev'
Requires-Dist: pytest ; extra == 'dev'
Requires-Dist: pytest-cov ; extra == 'dev'
Requires-Dist: pytest-flake8 ; extra == 'dev'
